calllogdb/__init__.py
calllogdb/async_calllog.py
calllogdb/calllog.py
calllogdb/py.typed
calllogdb/api/__init__.py
calllogdb/api/api_client.py
calllogdb/api/async_api_client.py
calllogdb/core/__init__.py
calllogdb/core/config.py
calllogdb/db/__init__.py
calllogdb/db/async_database.py
calllogdb/db/database.py
calllogdb/db/models.py
calllogdb/types/__init__.py
calllogdb/types/call.py
calllogdb/types/call_copy.py
calllogdb/types/calls.py
calllogdb/types/event.py
calllogdb/types/event_base.py
calllogdb/utils/__init__.py
calllogdb/utils/utils.py
calllogdb-0.2.4.dist-info/METADATA
calllogdb-0.2.4.dist-info/WHEEL
calllogdb-0.2.4.dist-info/licenses/LICENSE
calllogdb-0.2.4.dist-info/RECORD
