Metadata-Version: 2.4
Name: calllogdb
Version: 0.2.4
Summary: Библиотека для работы с call_log
Project-URL: Homepage, https://github.com/Mcn-BPA/CallLogDB
Author: deydysh
Author-email: Alexeyalexeyalexm <silaenckov2014@yandex.ru>, miomelliot <s89652158910@gmail.com>
License: CallLogDB Proprietary Internal Use Only License
License-File: LICENSE
Classifier: License :: Other/Proprietary License
Classifier: Operating System :: OS Independent
Classifier: Programming Language :: Python :: 3
Requires-Python: >=3.12
Requires-Dist: asyncpg>=0.30.0
Requires-Dist: dotenv>=0.9.9
Requires-Dist: httpx>=0.28.1
Requires-Dist: loguru>=0.7.3
Requires-Dist: psycopg[binary]>=3.2.10
Requires-Dist: pydantic>=2.11.9
Requires-Dist: python-dateutil>=2.9.0.post0
Requires-Dist: pyyaml>=6.0.2
Requires-Dist: requests>=2.32.5
Requires-Dist: sqlalchemy>=2.0.43
